Metadata-Version: 2.1
Name: flake8-constants
Version: 0.0.3
Summary: A Flake8 plugin to detect modifications of constants
Home-page: https://github.com/eneakllomollari/flake8-constants
Author: Enea Kllomollari
Author-email: eneakllomollari@gmail.com
License: MIT
Classifier: License :: OSI Approved :: MIT License
Classifier: Programming Language :: Python :: 3
Classifier: Programming Language :: Python :: 3.6
Classifier: Programming Language :: Python :: 3.7
Classifier: Programming Language :: Python :: 3.8
Classifier: Programming Language :: Python :: 3.9
Classifier: Framework :: Flake8
Requires-Python: >=3.6
License-File: LICENSE
Requires-Dist: flake8>=3.0.0
Provides-Extra: test
Requires-Dist: pytest; extra == "test"
Requires-Dist: pytest-cov; extra == "test"
